LICENSE
MANIFEST.in
README.md
requirements.txt
setup.cfg
setup.py
ckanext/__init__.py
ckanext/siu_harvester/__init__.py
ckanext/siu_harvester/plugin.py
ckanext/siu_harvester/harvesters/__init__.py
ckanext/siu_harvester/harvesters/siu_transp.py
ckanext/siu_harvester/tests/__init__.py
ckanext/siu_harvester/tests/factories.py
ckanext/siu_harvester/tests/test_harvest.py
ckanext_siu_harvester.egg-info/PKG-INFO
ckanext_siu_harvester.egg-info/SOURCES.txt
ckanext_siu_harvester.egg-info/dependency_links.txt
ckanext_siu_harvester.egg-info/entry_points.txt
ckanext_siu_harvester.egg-info/namespace_packages.txt
ckanext_siu_harvester.egg-info/top_level.txt