Metadata-Version: 2.1
Name: ckanext-siu-harvester
Version: 0.2.76
Summary: SIU Harvest
Home-page: https://github.com/avdata99/ckanext-siu-harvester
Author: Andres Vazquez
Author-email: andres@data99.com.ar
License: MIT
Keywords: CKAN harvest SIU Universid
Platform: UNKNOWN
Classifier: Development Status :: 4 - Beta
Classifier: License :: OSI Approved :: GNU Affero General Public License v3 or later (AGPLv3+)
Classifier: Programming Language :: Python :: 2.7
